{
    "name": "Global Information",
    "numberOfRequests": {
        "total": 12,
        "ok": 11,
        "ko": 1
    },
    "minResponseTime": {
        "total": 74,
        "ok": 74,
        "ko": 221
    },
    "maxResponseTime": {
        "total": 1534,
        "ok": 1534,
        "ko": 221
    },
    "meanResponseTime": {
        "total": 450,
        "ok": 471,
        "ko": 221
    },
    "standardDeviation": {
        "total": 422,
        "ok": 435,
        "ko": 0
    },
    "percentiles1": {
        "total": 228,
        "ok": 228,
        "ko": 221
    },
    "percentiles2": {
        "total": 559,
        "ok": 674,
        "ko": 221
    },
    "percentiles3": {
        "total": 1201,
        "ok": 1232,
        "ko": 221
    },
    "percentiles4": {
        "total": 1467,
        "ok": 1474,
        "ko": 221
    },
    "group1": {
    "name": "t < 800 ms",
    "count": 8,
    "percentage": 67
},
    "group2": {
    "name": "800 ms < t < 1200 ms",
    "count": 2,
    "percentage": 17
},
    "group3": {
    "name": "t > 1200 ms",
    "count": 1,
    "percentage": 8
},
    "group4": {
    "name": "failed",
    "count": 1,
    "percentage": 8
},
    "meanNumberOfRequestsPerSecond": {
        "total": 2.0,
        "ok": 1.8333333333333333,
        "ko": 0.16666666666666666
    }
}